<?xml version="1.0" encoding="utf-8"?>
<b t="Freni anteriori" >
<c i="0" t="configtype none title" >
<t s="1" t="Descrizione generale" >
<s i="AITAP70A4201001" t="Descrizione del freno anteriore">
</s>
</t>
<t s="6" t="Istruzioni di riparazione" >
<s i="AITAP70A4206001" t="Componenti del freno anteriore">
</s>
<s i="AITAP70A4206002" t="Ispezione delle pastiglie freno anteriore a bordo del veicolo">
</s>
<s i="AITAP70A4206003" t="Rimozione e installazione delle pastiglie freno anteriore">
</s>
<s i="AITAP70A4206004" t="Ispezione delle pastiglie freno anteriore">
</s>
<s i="AITAP70A4206005" t="Rimozione e installazione del disco freno anteriore">
</s>
<s i="AITAP70A4206006" t="Ispezione del disco del freno anteriore">
</s>
<s i="AITAP70A4206007" t="Rimozione e installazione della pinza del freno anteriore">
</s>
<s i="AITAP70A4206008" t="Smontaggio e rimontaggio della pinza freno anteriore">
</s>
<s i="AITAP70A4206009" t="Ispezione della pinza del freno anteriore">
</s>
</t>
<t s="7" t="Specifiche tecniche" >
<s i="AITAP70A4207001" t="Coppie di serraggio">
</s>
</t>
<t s="8" t="Attrezzatura speciale" >
<s i="AITAP70A4208001" t="Materiali di manutenzione e assistenza raccomandati">
</s>
<s i="AITAP70A4208002" t="Attrezzo speciale">
</s>
</t>
</c>
</b>
