<?xml version="1.0" encoding="utf-8"?>
<b t="Transmisión automática" >
<c i="0" t="configtype none title" >
<t s="0" t="Precauciones" >
<s i="ASPAP70B5100001" t="Medidas de precaución para el diagnóstico de problemas">
</s>
<s i="ASPAP70B5100003" t="Precauciones relacionadas con el sistema OBD">
</s>
<s i="ASPAP70B5100002" t="Medidas de precaución para el montaje y desmontaje">
</s>
</t>
<t s="1" t="Descripción general" >
<s i="ASPAP70B5101001" t="Descripción de la A/T">
</s>
<s i="ASPAP70B5101002" t="Descripción de las funciones del engranaje planetario/embrague/freno">
</s>
<s i="ASPAP70B5101003" t="Tabla del funcionamiento de los componentes de la A/T">
</s>
<s i="ASPAP70B5101004" t="Tabla de entrada/salida del sistema de control de cambio electrónico">
</s>
<s i="ASPAP70B5101005" t="Descripción general de los diagnósticos de la A/T">
</s>
<s i="ASPAP70B5101006" t="Descripción del sistema OBD">
</s>
</t>
<t s="2" t="Diagrama esquemático y de disposición" >
<s i="ASPAP70B5102001" t="Diagrama de entrada y salida del sistema de control de cambio electrónico">
</s>
<s i="ASPAP70B5102002" t="Diagrama del circuito del sistema de control de cambio electrónico">
</s>
</t>
<t s="3" t="Ubicación de los componentes" >
<s i="ASPAP70B5103001" t="Ubicación de los componentes del sistema electrónico de control de cambios">
</s>
</t>
<t s="4" t="Información y procedimientos de diagnóstico" >
<s i="ASPAP70B5104001" t="Inspección del sistema de control de A/T">
</s>
<s i="ASPAP70B5104002" t="Inspección del MIL (modelo Euro-OBD)">
</s>
<s i="ASPAP70B5104049" t="Inspección de la luz de advertencia de la transmisión (modelo no Euro OBD)">
</s>
<s i="ASPAP70B5104003" t="Comprobación del DTC">
</s>
<s i="ASPAP70B5104004" t="Borrado de DTC">
</s>
<s i="ASPAP70B5104005" t="Tabla de DTC">
</s>
<s i="ASPAP70B5104006" t="Tabla de la función a prueba de fallos">
</s>
<s i="ASPAP70B5104007" t="Datos de la herramienta de escaneado">
</s>
<s i="ASPAP70B5104008" t="Inspección visual">
</s>
<s i="ASPAP70B5104009" t="Comprobación básica de la A/T">
</s>
<s i="ASPAP70B5104010" t="Prueba de carretera">
</s>
<s i="ASPAP70B5104011" t="Prueba de carretera manual">
</s>
<s i="ASPAP70B5104012" t="Prueba del freno del motor">
</s>
<s i="ASPAP70B5104013" t="Prueba de calado del motor">
</s>
<s i="ASPAP70B5104014" t="Prueba de retardo">
</s>
<s i="ASPAP70B5104015" t="Prueba de presión de tuberías">
</s>
<s i="ASPAP70B5104016" t="Prueba de la posición &#34;P&#34;">
</s>
<s i="ASPAP70B5104017" t="Diagnóstico de los síntomas de la A/T">
</s>
<s i="ASPAP70B5104018" t="No es posible el cambio de engranaje al engranaje de 4ª">
</s>
<s i="ASPAP70B5104019" t="No hay enclavamiento">
</s>
<s i="ASPAP70B5104020" t="La luz indicadora de averías no se enciende con el encendido en posición &#34;ON&#34; y el motor detenido (pero se puede arrancar el motor) (modelos Euro-OBD)">
</s>
<s i="ASPAP70B5104021" t="El MIL permanece encendido tras arrancar el motor (modelo Euro-OBD)">
</s>
<s i="ASPAP70B5104050" t="La luz de advertencia de la transmisión no se enciende al colocar el encendido en la posición &#34;ON&#34; (modelos no Euro-OBD)">
</s>
<s i="ASPAP70B5104051" t="La luz de advertencia de la transmisión permanece encendida con el encendido en &#34;ON&#34; (modelos no Euro-OBD)">
</s>
<s i="ASPAP70B5104022" t="DTC P0602">
</s>
<s i="ASPAP70B5104023" t="DTC P062F / P1702">
</s>
<s i="ASPAP70B5104024" t="DTC P0705">
</s>
<s i="ASPAP70B5104025" t="DTC P0707">
</s>
<s i="ASPAP70B5104026" t="DTC P0711">
</s>
<s i="ASPAP70B5104027" t="DTC P0712">
</s>
<s i="ASPAP70B5104028" t="DTC P0713">
</s>
<s i="ASPAP70B5104029" t="DTC P0717">
</s>
<s i="ASPAP70B5104030" t="DTC P0722">
</s>
<s i="ASPAP70B5104031" t="DTC P0741 / P0742">
</s>
<s i="ASPAP70B5104032" t="DTC P0751 / P0752 / P0756 / P0757">
</s>
<s i="ASPAP70B5104033" t="DTC P0787">
</s>
<s i="ASPAP70B5104034" t="DTC P0788">
</s>
<s i="ASPAP70B5104035" t="DTC P0961">
</s>
<s i="ASPAP70B5104036" t="DTC P0962">
</s>
<s i="ASPAP70B5104037" t="DTC P0963">
</s>
<s i="ASPAP70B5104038" t="DTC P0973 / P0976">
</s>
<s i="ASPAP70B5104039" t="DTC P0974 / P0977">
</s>
<s i="ASPAP70B5104040" t="DTC P1706">
</s>
<s i="ASPAP70B5104041" t="DTC P1878">
</s>
<s i="ASPAP70B5104042" t="DTC P2762">
</s>
<s i="ASPAP70B5104043" t="DTC P2763">
</s>
<s i="ASPAP70B5104044" t="DTC P2764">
</s>
<s i="ASPAP70B5104045" t="DTC U0073">
</s>
<s i="ASPAP70B5104046" t="DTC U0100">
</s>
<s i="ASPAP70B5104047" t="Inspección del TCM y sus circuitos">
</s>
<s i="ASPAP70B5104048" t="Comprobación del circuito de alimentación eléctrica y a masa del TCM">
</s>
</t>
<t s="6" t="Instrucciones de reparación" >
<s i="ASPAP70B5106001" t="Reinicio del control de aprendizaje del TCM">
</s>
<s i="ASPAP70B5106002" t="Inspección del nivel de ATF">
</s>
<s i="ASPAP70B5106003" t="Cambio del ATF">
</s>
<s i="ASPAP70B5106004" t="Componentes del conjunto de la palanca selectora">
</s>
<s i="ASPAP70B5106005" t="Extracción e instalación del conjunto de la palanca selectora">
</s>
<s i="ASPAP70B5106006" t="Inspección del conjunto de la palanca selectora">
</s>
<s i="ASPAP70B5106007" t="Inspección del interruptor de corte de O/D">
</s>
<s i="ASPAP70B5106008" t="Inspección de interruptor de la posición P (modelo de arranque por pulsación sin llave)">
</s>
<s i="ASPAP70B5106009" t="Inspección de la válvula solenoide de bloqueo del cambio">
</s>
<s i="ASPAP70B5106010" t="Liberación manual del bloqueo de cambio">
</s>
<s i="ASPAP70B5106011" t="Componentes del cable de selección">
</s>
<s i="ASPAP70B5106012" t="Extracción e instalación del cable de selección">
</s>
<s i="ASPAP70B5106013" t="Ajuste del cable de selección">
</s>
<s i="ASPAP70B5106014" t="Extracción e instalación del sensor de posición de la transmisión">
</s>
<s i="ASPAP70B5106015" t="Inspección y ajuste del sensor de posición de la transmisión">
</s>
<s i="ASPAP70B5106016" t="Extracción e instalación del cable de interbloqueo de la llave (modelos con interruptor de encendido)">
</s>
<s i="ASPAP70B5106017" t="Inspección del cable de interbloqueo de la llave (modelos con interruptor de encendido)">
</s>
<s i="ASPAP70B5106018" t="Extracción e instalación del sensor de velocidad del eje de salida">
</s>
<s i="ASPAP70B5106019" t="Inspección del sensor de velocidad del eje de salida">
</s>
<s i="ASPAP70B5106020" t="Extracción e instalación del sensor de velocidad del eje de entrada">
</s>
<s i="ASPAP70B5106021" t="Inspección del sensor de velocidad del eje de entrada">
</s>
<s i="ASPAP70B5106022" t="Extracción e instalación del conjunto de colador de aceite de A/T">
</s>
<s i="ASPAP70B5106023" t="Inspección del conjunto del colador de aceite y el cárter de aceite de A/T">
</s>
<s i="ASPAP70B5106024" t="Extracción e instalación del sensor de temperatura del ATF">
</s>
<s i="ASPAP70B5106025" t="Inspección del sensor de temperatura del ATF">
</s>
<s i="ASPAP70B5106026" t="Extracción e instalación del conjunto del cuerpo de válvula">
</s>
<s i="ASPAP70B5106027" t="Inspección en el vehículo de la válvula solenoide">
</s>
<s i="ASPAP70B5106028" t="Extracción e instalación de la válvula solenoide">
</s>
<s i="ASPAP70B5106029" t="Inspección de la válvula solenoide">
</s>
<s i="ASPAP70B5106030" t="Extracción e instalación del TCM">
</s>
<s i="ASPAP70B5106031" t="Inspección del relé de A/T">
</s>
<s i="ASPAP70B5106032" t="Sustitución del sello de aceite lateral del diferencial">
</s>
<s i="ASPAP70B5106033" t="Inspección de las mangueras del refrigerador del ATF">
</s>
<s i="ASPAP70B5106034" t="Sustitución de las mangueras del refrigerador del ATF">
</s>
<s i="ASPAP70B5106035" t="Componentes del conjunto de A/T">
</s>
<s i="ASPAP70B5106036" t="Desmontaje y montaje del conjunto de la A/T">
</s>
<s i="ASPAP70B5106037" t="Desmontaje del conjunto de la A/T">
</s>
<s i="ASPAP70B5106038" t="Componentes del conjunto de la bomba de aceite">
</s>
<s i="ASPAP70B5106039" t="Desmontaje y montaje del conjunto de la bomba de aceite">
</s>
<s i="ASPAP70B5106040" t="Inspección del conjunto de la bomba de aceite">
</s>
<s i="ASPAP70B5106041" t="Componentes del conjunto del embrague de directa">
</s>
<s i="ASPAP70B5106042" t="Inspección preliminar del conjunto del embrague directo">
</s>
<s i="ASPAP70B5106043" t="Desmontaje y montaje del conjunto del embrague directo">
</s>
<s i="ASPAP70B5106044" t="Inspección del conjunto del embrague directo">
</s>
<s i="ASPAP70B5106045" t="Componentes del conjunto del embrague de avance y el embrague invertido">
</s>
<s i="ASPAP70B5106046" t="Inspección preliminar del conjunto del embrague de avance y el embrague invertido">
</s>
<s i="ASPAP70B5106047" t="Desmontaje y montaje del conjunto del embrague de avance y el embrague invertido">
</s>
<s i="ASPAP70B5106048" t="Inspección del conjunto de embrague de avance y embrague invertido">
</s>
<s i="ASPAP70B5106049" t="Componentes del conjunto de pistón del freno de 2ª">
</s>
<s i="ASPAP70B5106050" t="Desmontaje y montaje del conjunto de pistón del freno de 2ª">
</s>
<s i="ASPAP70B5106051" t="Componentes del conjunto de la cubierta trasera del transeje (pistón del freno de O/D y de inercia de 2ª)">
</s>
<s i="ASPAP70B5106052" t="Desmontaje y montaje del conjunto de la cubierta trasera del transeje (pistón del freno de O/D y de inercia de 2ª)">
</s>
<s i="ASPAP70B5106053" t="Inspección del conjunto de la cubierta trasera del transeje (pistón del freno de O/D y de inercia de 2ª)">
</s>
<s i="ASPAP70B5106054" t="Componentes del conjunto del contraeje">
</s>
<s i="ASPAP70B5106055" t="Desmontaje y montaje del conjunto de contraeje">
</s>
<s i="ASPAP70B5106056" t="Componentes del conjunto del diferencial">
</s>
<s i="ASPAP70B5106057" t="Desmontaje y montaje del conjunto del diferencial">
</s>
<s i="ASPAP70B5106058" t="Inspección del conjunto del diferencial">
</s>
<s i="ASPAP70B5106059" t="Componentes del conjunto del cuerpo de válvula">
</s>
<s i="ASPAP70B5106060" t="Desmontaje y montaje del conjunto del cuerpo de válvula">
</s>
<s i="ASPAP70B5106061" t="Desmontaje y montaje del alojamiento del convertidor de par">
</s>
<s i="ASPAP70B5106062" t="Desmontaje y montaje de la caja del transeje">
</s>
<s i="ASPAP70B5106063" t="Inspección y ajuste del conjunto de A/T">
</s>
<s i="ASPAP70B5106064" t="Montaje del conjunto de la A/T">
</s>
</t>
<t s="7" t="Especificaciones" >
<s i="ASPAP70B5107001" t="Especificaciones acerca de los pares de apriete">
</s>
</t>
<t s="8" t="Herramientas y equipos especiales" >
<s i="ASPAP70B5108001" t="Material de servicio recomendado">
</s>
<s i="ASPAP70B5108002" t="Herramienta especial">
</s>
</t>
</c>
</b>
