<?xml version="1.0" encoding="utf-8"?>
<b t="Sustav podmazivanja motora" >
<c i="0" t="configtype none title" >
<t s="1" t="Opći opis" >
<s i="AHRAP70A1501001" t="Opis podmazivanja motora">
</s>
</t>
<t s="4" t="Dijagnostičke informacije i procedure" >
<s i="AHRAP70A1504001" t="Provjera tlaka ulja">
</s>
</t>
<t s="6" t="Upute za popravak" >
<s i="AHRAP70A1506001" t="Zamjena motornog ulja i filtra">
</s>
<s i="AHRAP70A1506002" t="Pregled prekidača tlaka ulja na vozilu">
</s>
<s i="AHRAP70A1506003" t="Dijelovi korita ulja i grubog filtra pumpe ulja">
</s>
<s i="AHRAP70A1506004" t="Uklanjanje i ugradnja korita ulja i grubog filtra pumpe ulja">
</s>
<s i="AHRAP70A1506005" t="Komponente sklopa pumpe ulja">
</s>
<s i="AHRAP70A1506006" t="Uklanjanje i ugradnja sklopa pumpe ulja">
</s>
<s i="AHRAP70A1506007" t="Rastavljanje i sastavljanje pumpe ulja">
</s>
<s i="AHRAP70A1506008" t="Pregled pumpe ulja">
</s>
</t>
<t s="7" t="Specifikacije" >
<s i="AHRAP70A1507001" t="Specifikacije momenta pritezanja">
</s>
</t>
<t s="8" t="Specijalni alati i oprema" >
<s i="AHRAP70A1508001" t="Preporučeni servisni materijal">
</s>
<s i="AHRAP70A1508002" t="Specijalni alat">
</s>
</t>
</c>
</b>
