<?xml version="1.0" encoding="utf-8"?>
<b t="Σύστημα Λίπανσης Κινητήρα" >
<c i="0" t="configtype none title" >
<t s="1" t="Γενική Περιγραφή" >
<s i="AGKAP70A1501001" t="Περιγρα&#248;ή της Λίπανσης του Κινητήρα">
</s>
</t>
<t s="4" t="Διαγνωστικές Πληροφορίες και Διαδικασίες" >
<s i="AGKAP70A1504001" t="Έλεγχος Της Πίεσης Λαδιού">
</s>
</t>
<t s="6" t="Οδηγίες Επισκευής" >
<s i="AGKAP70A1506001" t="Αντικατάσταση Λαδιού και Φίλτρου Λαδιού του Κινητήρα">
</s>
<s i="AGKAP70A1506002" t="Επιθεώρηση Επί του Αυτοκινήτου του Διακόπτη Πίεσης Λαδιού">
</s>
<s i="AGKAP70A1506003" t="Εξαρτήματα του Κάρτερ Λαδιού και της Σήτας της Αντλίας Λαδιού">
</s>
<s i="AGKAP70A1506004" t="Α&#248;αίρεση και Τοποθέτηση Κάρτερ Λαδιού και της Σήτας της Αντλίας Λαδιού">
</s>
<s i="AGKAP70A1506005" t="Εξαρτήματα Συγκροτήματος Αντλίας Λαδιού">
</s>
<s i="AGKAP70A1506006" t="Α&#248;αίρεση και Τοποθέτηση του Συγκροτήματος Αντλίας Λαδιού">
</s>
<s i="AGKAP70A1506007" t="Αποσυναρμολόγηση και Επανασυναρμολόγηση Συγκροτήματος Αντλίας Λαδιού">
</s>
<s i="AGKAP70A1506008" t="Επιθεώρηση της Αντλίας Λαδιού">
</s>
</t>
<t s="7" t="Προδιαγραφές" >
<s i="AGKAP70A1507001" t="Προδιαγραφές Ροπών Σύσφιξης">
</s>
</t>
<t s="8" t="Ειδικά Εργαλεία και Εξοπλισμός" >
<s i="AGKAP70A1508001" t="Προτεινόμενα Υλικά Συντήρησης">
</s>
<s i="AGKAP70A1508002" t="Ειδικό Εργαλείο">
</s>
</t>
</c>
</b>
